{
    "source": {
        "id": "abc-news-au",
        "name": "ABC News (AU)"
    },
    "author": "Dylan Welch And Casey Briggs",
    "title": "'We are not practising the 1.5-metres rule': Public service workers say offices ignoring coronavirus advice",
    "description": "Public sector workers have told the ABC that they are being prevented from working remotely by the federal and state governments, despite pleas for Australians to practice social distancing and stay at home.",
    "url": "https://www.abc.net.au/news/2020-03-25/public-service-workers-say-offices-ignoring-coronavirus-advice/12088120",
    "urlToImage": "https://www.abc.net.au/news/image/12089104-16x9-700x394.jpg",
    "publishedAt": "2020-03-25T03:23:23Z",
    "content": "Updated \r\nMarch 25, 2020 14:29:45\r\nThousands of Australian public service employees in non-essential areas are being prevented from working remotely by the federal and state governments, despite repeated demands for people to take the global coronavirus pande\u2026 [+8662 chars]"
}