{
    "source": {
        "id": "politico",
        "name": "Politico"
    },
    "author": "Nolan D. McCaskill",
    "title": "Governors see possible 'flattening' of the curve in latest coronavirus data",
    "description": "Improvements in New York, New Jersey, California and Washington raise hopes, but \"this isn\u2019t over,\" one governor warns.",
    "url": "https://www.politico.com/news/2020/04/06/coronavirus-curve-governors-168865",
    "urlToImage": "https://static.politico.com/11/3a/e04850bd496eb9fec7a98080e49c/200406-cuomo-ap-773.jpg",
    "publishedAt": "2020-04-06T22:31:41Z",
    "content": "Those are all good signs and, again, would suggest a possible flattening of the curve\" that tracks the number of cases, he said.\r\nNext door, New Jersey now has the second-worst outbreak of the virus. More than 41,000 people in New Jersey have tested positive,\u2026 [+2231 chars]"
}