{
    "source": {
        "id": "bbc-news",
        "name": "BBC News"
    },
    "author": null,
    "title": "Liverpool v Atletico Madrid virus link an 'interesting hypothesis'",
    "description": "A government adviser says speculation over a possible link between coronavirus cases in Liverpool and the club's Champions League match with Atletico Madrid last month is an \"interesting hypothesis\".",
    "url": "https://www.bbc.co.uk/sport/football/52362099",
    "urlToImage": "https://ichef.bbci.co.uk/onesport/cps/624/cpsprodpb/DA30/production/_111865855_anfieldfan_getty.jpg",
    "publishedAt": "2020-04-20T20:32:46Z",
    "content": "More than 52,000 fans watched as Liverpool lost 3-2 to Atletico Madrid at Anfield on 11 March, a result that sealed the holders' elimination from the competition\r\nSpeculation over a possible link between coronavirus cases in Liverpool and the club's Champions\u2026 [+3583 chars]"
}