{
    "source": {
        "id": "techcrunch",
        "name": "TechCrunch"
    },
    "author": "Zack Whittaker",
    "title": "Zoom sued by shareholder for \u2018overstating\u2019 security claims",
    "description": "Zoom has been served with another class action lawsuit \u2014 this time by one of its shareholders, who says he lost money after the company \u201coverstated\u201d its security measures, which led its share price to tank. The video conferencing giant has seen its daily usag\u2026",
    "url": "http://techcrunch.com/2020/04/08/zoom-sued-shareholder-security/",
    "urlToImage": "https://techcrunch.com/wp-content/uploads/2020/04/GettyImages-1208677866.jpg?w=600",
    "publishedAt": "2020-04-08T17:25:31Z",
    "content": "Zoom has been served with another class action lawsuit this time by one of its shareholders, who says he lost money after the company \u201coverstated\u201d its security measures, which led its share price to tank.\r\nThe video conferencing giant has seen its daily usage\u2026 [+1630 chars]"
}