{
    "source": {
        "id": "the-hindu",
        "name": "The Hindu"
    },
    "author": "A Correspondent",
    "title": "Coronavirus | Youth held for spreading fake information on COVID-19 in Tripura",
    "description": "No positive case detected in the State on Sunday, says Chief Minister",
    "url": "https://www.thehindu.com/news/national/coronavirus-youth-held-for-spreading-fake-information-on-covid-19-in-tripura/article31199472.ece",
    "urlToImage": "https://www.thehindu.com/news/national/4pun4b/article31199471.ece/ALTERNATES/LANDSCAPE_615/vbk-fake-news",
    "publishedAt": "2020-03-29T14:14:33Z",
    "content": "The Tripura police on Sunday arrested a youth for allegedly spreading fake news on the novel coronavirus situation in the State. They claimed he was posting false or fabricated information over reported detection of positive cases.\r\nAlso read | Centre asks so\u2026 [+950 chars]"
}