{
    "source": {
        "id": "bbc-news",
        "name": "BBC News"
    },
    "author": null,
    "title": "Former McLaren boss Dennis creates NHS free meals scheme",
    "description": "Former McLaren boss Ron Dennis has created a scheme to supply a million free meals to NHS workers during the coronavirus crisis.",
    "url": "https://www.bbc.co.uk/sport/formula1/52186473",
    "urlToImage": "https://ichef.bbci.co.uk/onesport/cps/624/cpsprodpb/FA53/production/_111638046_rondennis.jpg",
    "publishedAt": "2020-04-06T14:08:31Z",
    "content": "Dennis won multiple F1 world championships with McLaren\r\nFormer McLaren boss Ron Dennis has created a scheme to supply a million free meals to NHS workers during the coronavirus crisis.\r\nDennis says his foundation has put in place a \u00a31.5m budget and joined fo\u2026 [+2849 chars]"
}