{
    "source": {
        "id": "news24",
        "name": "News24"
    },
    "author": null,
    "title": "News24.com | Ramaphosa summonses Ndabeni-Abrahams to a meeting over lockdown lunch",
    "description": "President Cyril Ramaphosa has summoned Communications Minister Stella Ndabeni-Abrahams, to a meeting to discuss a purported social media post of her having lunch with former deputy higher education minister Mduduzi Manana.",
    "url": "https://www.news24.com/SouthAfrica/News/ramaphosa-summonses-ndabeni-abrahams-to-a-meeting-over-lockdown-lunch-20200407",
    "urlToImage": "http://cdn.24.co.za/files/Cms/General/d/9080/30af993f831745d4b9125cc8c642069f.jpg",
    "publishedAt": "2020-04-07T12:30:34Z",
    "content": "President Cyril Ramaphosa has summoned\u00a0Communications Minister Stella Ndabeni-Abrahams, to a meeting to discuss a purported social media post of her having lunch with former deputy higher education minister Mduduzi Manana.\r\nThe picture sparked debate on wheth\u2026 [+3316 chars]"
}