{
    "source": {
        "id": "associated-press",
        "name": "Associated Press"
    },
    "author": "",
    "title": "Idaho Gov. Brad Little issues statewide stay-at-home order",
    "description": "BOISE, Idaho (AP) \u2014 Idaho Gov. Brad Little issues statewide stay-at-home order.",
    "url": "https://apnews.com/a40213c0e09bc11a45cbfd771ab6312f",
    "urlToImage": "https://bloximages.newyork1.vip.townnews.com/roanoke.com/content/tncms/custom/image/00f1ee32-f2d0-11e6-9926-f7249dbfe53a.jpg",
    "publishedAt": "2020-03-25T19:35:50Z",
    "content": "Keep it Clean. Please avoid obscene, vulgar, lewd,\r\nracist or sexually-oriented language.PLEASE TURN OFF YOUR CAPS LOCK.Don't Threaten. Threats of harming another\r\nperson will not be tolerated.Be Truthful. Don't knowingly lie about anyone\r\nor anything.Be Nice\u2026 [+246 chars]"
}