{
    "source": {
        "id": "techradar",
        "name": "TechRadar"
    },
    "author": "John Brandon",
    "title": "What makes a remote working team successful?",
    "description": "Managing employees who are working from home requires an extra focus on health and well-being for helping with productivity.",
    "url": "https://www.techradar.com/news/what-makes-a-remote-working-team-successful",
    "urlToImage": "https://cdn.mos.cms.futurecdn.net/nBWumA93PCj9Wa6HNce6hH-1200-80.jpg",
    "publishedAt": "2020-04-16T10:17:40Z",
    "content": "Success at work just became much harder to define. Now that many of us are working at home due to the worldwide pandemic, theres a level playing field. We can track sales metrics or how many tasks a worker performs in a week, but intangibles (such as being a \u2026 [+5737 chars]"
}