{
    "source": {
        "id": "independent",
        "name": "Independent"
    },
    "author": "Gino Spocchia, Gino Spocchia",
    "title": "Coronavirus: Crime plummets across US amid lockdown",
    "description": "As Americans stay at home to stop the spread of coronavirus, crime rates have begun to collapse in big cities",
    "url": "https://www.independent.co.uk/news/world/americas/coronavirus-crime-new-york-la-chicago-buffalo-police-lockdown-a9428456.html",
    "urlToImage": "https://static.independent.co.uk/s3fs-public/thumbnails/image/2020/03/26/15/police-car.jpg",
    "publishedAt": "2020-03-26T18:23:57Z",
    "content": "Crime has plummeted in some of Americas biggest cities, after millions were ordered to stay at home amid the coronavirus pandemic.\u00a0\r\nWithout crowded public spaces, transport use and open businesses, criminals have almost nowhere to commit offences. That comes\u2026 [+1885 chars]"
}