{
    "source": {
        "id": "techradar",
        "name": "TechRadar"
    },
    "author": "Steve McCaskill",
    "title": "Ofcom suspends regulation work during coronavirus crisis",
    "description": "Ofcom welcomes measures taken by communications providers.",
    "url": "https://www.techradar.com/uk/news/ofcom-suspends-regulation-work-during-coronavirus-crisis",
    "urlToImage": "https://cdn.mos.cms.futurecdn.net/LaSKmcNCkhfTVxQHMqkz6g-1200-80.jpg",
    "publishedAt": "2020-03-25T12:03:21Z",
    "content": "Ofcom has suspended work on proposed new regulations for the communications industry during the coronavirus outbreak and has issued advice for consumers who are more reliant on their broadband service during the current restrictions on movement.\r\nIn a televis\u2026 [+2534 chars]"
}