{
    "source": {
        "id": "cbc-news",
        "name": "CBC News"
    },
    "author": "The Canadian Press",
    "title": "What's happened in Canada since WHO declared COVID-19 a pandemic",
    "description": "Here are some key developments for Canada since COVID-19 was declared a pandemic a month ago.",
    "url": "https://www.cbc.ca/news/politics/covid-19-timeline-canada-who-pandemic-1.5529920",
    "urlToImage": "https://i.cbc.ca/1.5529964.1586632836!/cumulusImage/httpImage/image.jpg_gen/derivatives/16x9_620/covid-19-test-kits.jpg",
    "publishedAt": "2020-04-11T19:48:08Z",
    "content": "Saturday marks one month since the World Health Organization declared COVID-19 a global pandemic.\r\nHere are some key developments for Canada since then:\r\nMarch 11: Prime Minister Justin Trudeau promises $1 billion for COVID-19 to help the health-care system a\u2026 [+6076 chars]"
}