{
    "source": {
        "id": "cbs-news",
        "name": "CBS News"
    },
    "author": "CBS News",
    "title": "Arts organizations bring the experience home to kids",
    "description": "Lights are out at theaters and museums around the country due to the coronavirus pandemic. But arts organizations are finding ways to stay connected, even with the youngest art lovers. \"Lincoln Center at Home\" is just one initiative that offers free children'\u2026",
    "url": "https://www.cbsnews.com/video/arts-organizations-bring-the-experience-home-to-kids/",
    "urlToImage": "https://cbsnews1.cbsistatic.com/hub/i/r/2020/04/07/46ed6661-8516-4780-9b51-70ff9acff305/thumbnail/1200x630/6a44850cf5fb77f465d24814f7daf5e6/watchinglincolncenterartlesson-2053497-640x360.jpg",
    "publishedAt": "2020-04-07T18:12:37Z",
    "content": "Watch CBSN Live\r\nCopyright \u00a9 2020 CBS Interactive Inc. All rights reserved."
}