{
    "source": {
        "id": "politico",
        "name": "Politico"
    },
    "author": "Alice Miranda Ollstein, Dan Goldberg and Nolan D. McCaskill",
    "title": "Hot spots erupt in farm belt states where governors insist lockdowns aren\u2019t needed",
    "description": "Cases in parts of the heartland are starting to spike, raising concern about new hot spots that could quash Trump\u2019s push to reopen the economy and extend the public health crisis into the summer.",
    "url": "https://www.politico.com/news/2020/04/15/coronavirus-hot-spots-farm-belt-189272",
    "urlToImage": "https://static.politico.com/2e/74/a7b0bf1f450a8ca724821d7126f2/200415-asa-hutchinson-ap-773.jpg",
    "publishedAt": "2020-04-16T00:02:25Z",
    "content": "Trump and red state governors for weeks have fairly bragged about how large parts of the farm belt have escaped the ravages of the virus without the enforced shelter-in-place policies common on both coasts. Its still unclear whether the states actually flatte\u2026 [+6352 chars]"
}