{
    "source": {
        "id": "the-hill",
        "name": "The Hill"
    },
    "author": "Joe Concha",
    "title": "Fox's Hilton urges holdout GOP governors to 'shut things down everywhere'",
    "description": "Fox News host Steve Hilton is calling on Republicans governors in nine states who have not issued stay-at-home orders to do so to help slow the spread of the novel coronavirus in an effort to accelerate the return of the...",
    "url": "https://thehill.com/homenews/media/491365-foxs-hilton-urges-holdout-gop-governors-to-shut-things-down-everywhere",
    "urlToImage": "https://thehill.com/sites/default/files/reynolds-kim-getty_0.jpg",
    "publishedAt": "2020-04-06T17:17:34Z",
    "content": "Fox News host Steve Hilton\u00a0is calling on Republicans governors in nine states who have not issued stay-at-home orders to do so to help slow the spread of the novel coronavirus in an effort to accelerate the return of the U.S. economy.\r\n\"Last week, I said, ope\u2026 [+2803 chars]"
}