{
    "source": {
        "id": "the-irish-times",
        "name": "The Irish Times"
    },
    "author": null,
    "title": "Coronavirus: The full list of new restrictions",
    "description": "Varadkar urges everyone to stay at home for two weeks except in limited circumstances",
    "url": "https://www.irishtimes.com/news/ireland/irish-news/coronavirus-the-full-list-of-new-restrictions-1.4214248",
    "urlToImage": "https://www.irishtimes.com/image-creator/?id=1.4214246&origw=1440",
    "publishedAt": "2020-03-27T21:59:00Z",
    "content": "On Friday night, Taoiseach Leo Varadkar announced a range of new restrictions aimed at curbing the spread of coronavirus. From midnight until Easter Sunday, April 12th, everyone must stay at home except in the following circumstances:\r\n<ul><li>To travel to an\u2026 [+823 chars]"
}