{
    "source": {
        "id": "the-wall-street-journal",
        "name": "The Wall Street Journal"
    },
    "author": "Shane O\u2019Mara",
    "title": "Why Walking Matters -- Now More Than Ever...",
    "description": "Our upright gait is not just a defining feature of what it means to be human. It also makes our bodies and brains work better.",
    "url": "https://www.wsj.com/articles/why-walking-mattersnow-more-than-ever-11587182460",
    "urlToImage": "https://images.wsj.net/im-176247/social",
    "publishedAt": "2020-04-18T13:55:37Z",
    "content": "Why does walking make us feel good? We all know that a satisfying stroll changes our outlook. Perhaps we realize it all the more today, when so many of us are hunkered down and this simple activity is a challenge. But walking is especially important now, with\u2026 [+281 chars]"
}