{
    "source": {
        "id": "national-review",
        "name": "National Review"
    },
    "author": "Zachary Evans, Zachary Evans",
    "title": "Florida Gov. Ron DeSantis to Issue Stay-at-Home Order for Entire State",
    "description": "The order, to be enforced for the entire month of April, will ban all non-essential outside activities.",
    "url": "https://www.nationalreview.com/news/florida-gov-ron-desantis-to-issue-stay-at-home-order-for-entire-state/",
    "urlToImage": "https://i0.wp.com/www.nationalreview.com/wp-content/uploads/2020/04/Ron-Densantis.jpg?fit=1200%2C700&ssl=1",
    "publishedAt": "2020-04-01T18:11:40Z",
    "content": null
}