{
    "source": {
        "id": "rte",
        "name": "RTE"
    },
    "author": "Paschal Sheehy",
    "title": "Neighbourhood watch: Cork street enjoy classic films",
    "description": "Cinemas may be closed but around 20 neighbours in Cork have found a way to go to the movies without leaving the street where they live.",
    "url": "https://www.rte.ie/news/2020/0411/1130011-street-cinema-cork-covid-19/",
    "urlToImage": "https://img.rasset.ie/00141a5c-1600.jpg",
    "publishedAt": "2020-04-11T16:53:06Z",
    "content": "Cinemas may be closed but around 20 neighbours in Cork have found a way to go to the movies without leaving the street where they live.\r\nResidents of Frankfield Terrace have been enjoying classics from the comfort of their front gardens.\u00a0\r\nTheatre company pro\u2026 [+2924 chars]"
}