{
    "source": {
        "id": "nbc-news",
        "name": "NBC News"
    },
    "author": "NBCNews.com",
    "title": "U.K. prime minster orders country to 'stay at home'",
    "description": "In a televised address to the nation, British Prime Minister Boris Johnson said he wanted to \"give the British people a very simple instruction: You must stay at home.\"",
    "url": "https://www.nbcnews.com/now/video/british-prime-minister-boris-johnson-orders-country-to-stay-at-home-to-fight-coronavirus-spread-81112645558",
    "urlToImage": "https://media13.s-nbcnews.com/j/MSNBC/Components/Video/202003/ott_now_johnson_200323_1920x1080.nbcnews-fp-1200-630.jpg",
    "publishedAt": "2020-03-23T21:26:11Z",
    "content": null
}