{
    "source": {
        "id": "al-jazeera-english",
        "name": "Al Jazeera English"
    },
    "author": "Dr Sara Kayat",
    "title": "Doctor's Note: How to stay healthy during lockdown",
    "description": "A doctor explains the four pillars of health and how you can adhere to them during the coronavirus pandemic.",
    "url": "https://www.aljazeera.com/indepth/features/doctor-note-stay-healthy-lockdown-200410150245258.html",
    "urlToImage": "https://www.aljazeera.com/mritems/Images/2020/3/23/ee6275379b6b4ef6b7d18adaa954ff48_18.jpg",
    "publishedAt": "2020-04-11T11:57:26Z",
    "content": "With our usual routines going out window and the thought of staying in your pyjamas all day becoming ever more tempting, it is more important than ever to stay healthy during the lockdown.\r\nThis may require you to think a little outside of the box, but you sh\u2026 [+8253 chars]"
}