{
    "source": {
        "id": "independent",
        "name": "Independent"
    },
    "author": "Jean Lee, Jean Lee",
    "title": "'Listen up, dips***s': Kentucky mayor posts no-nonsense coronavirus advice",
    "description": "As cases steadily increase, leaders urge people to stay inside. Gabe Brown didn't hold back",
    "url": "https://www.independent.co.uk/news/world/americas/kentucky-mayor-facebook-coronavirus-stay-at-home-governor-a9429271.html",
    "urlToImage": "https://static.independent.co.uk/s3fs-public/thumbnails/image/2020/03/26/19/nhs-staff-patient.jpg",
    "publishedAt": "2020-03-26T23:18:13Z",
    "content": "A mayor in Kentucky has come up with an unusually frank warning about the dangers of the coronavirus for his constituents.\r\nGabe Brown, mayor of Walton, posted in the Boone County Neighborhood Facebook group: \"Listen up dipsh***s and sensible people.\r\n\"I migh\u2026 [+2666 chars]"
}