{
    "source": {
        "id": "politico",
        "name": "Politico"
    },
    "author": "Debra Kahn and Carla Marinucci",
    "title": "Bend it like the Bay Area: Doctors see flatter curve after 2 weeks of social isolation",
    "description": "After 14 days, doctors at area hospitals are now reporting fewer cases than they expected to see at this point.",
    "url": "https://www.politico.com/states/california/story/2020/03/30/bend-it-like-the-bay-area-doctors-see-flatter-curve-after-2-weeks-of-social-isolation-1269663",
    "urlToImage": "https://static.politico.com/30/26/5387116f4358b2019d372e295656/webp.net-resizeimage%20(1).jpg",
    "publishedAt": "2020-03-31T02:03:46Z",
    "content": "A relatively empty Golden Gate Bridge. | AP Photo\r\nSAN FRANCISCO State leaders and doctors are cautiously optimistic that the Bay Area's early moves to lock down residents two weeks ago have prevented surges of coronavirus patients from overwhelming the regio\u2026 [+6859 chars]"
}