{
    "source": {
        "id": "msnbc",
        "name": "MSNBC"
    },
    "author": "MSNBC.com",
    "title": "South Carolina governor issues weak 'home or work' COVID-19 order",
    "description": "Rachel Maddow remarks on South Carolina Governor Henry McMaster's \"home or work\" order, which is not as strict as a stay-at-home order and allows several major loopholes that weaken the effectiveness of the order at preventing the spread of coronavirus in his\u2026",
    "url": "https://www.msnbc.com/rachel-maddow/watch/south-carolina-governor-issues-weak-home-or-work-covid-19-order-81721925549",
    "urlToImage": "https://media13.s-nbcnews.com/j/MSNBC/Components/Video/202004/n_maddow_sc_200406_1920x1080.nbcnews-fp-1200-630.jpg",
    "publishedAt": "2020-04-07T04:25:55Z",
    "content": null
}