{
    "source": {
        "id": "football-italia",
        "name": "Football Italia"
    },
    "author": "Football Italia staff",
    "title": "Diaconale: 'Anti-Lazio media in unison'",
    "description": "Director of communications Arturo Diaconale claims \u201cthe media move in unison to criticise Lazio and President Claudio Lotito. There is an anti-Lazio conformity.\u201d",
    "url": "https://www.football-italia.net/152042/diaconale-anti-lazio-media-unison",
    "urlToImage": null,
    "publishedAt": "2020-04-11T15:10:39Z",
    "content": "Director of communications Arturo Diaconale claims \u201cthe media move in unison to criticise Lazio and President Claudio Lotito. There is an anti-Lazio conformity.\u201d\r\nThe Aquile have been the most vocal in trying to resume training even as the coronavirus pandemi\u2026 [+2087 chars]"
}