{
    "source": {
        "id": "cbc-news",
        "name": "CBC News"
    },
    "author": null,
    "title": "City mulls hotel purchase to house homeless during pandemic and beyond - CBC.ca",
    "description": "<ol><li>City mulls hotel purchase to house homeless during pandemic and beyond\u00a0\u00a0CBC.ca\r\n</li><li>City of Ottawa to spend $11.4M to support homeless population during coronavirus pandemic\u00a0\u00a0Global News\r\n</li><li>Federal government has limited ability to ramp up\u2026",
    "url": "https://www.cbc.ca/news/canada/ottawa/buying-hotels-ottawa-1.5539204",
    "urlToImage": "https://i.cbc.ca/1.5539205.1587430961!/fileImage/httpImage/image.jpg_gen/derivatives/16x9_620/homeless-shelters.jpg",
    "publishedAt": "2020-04-21T15:01:00Z",
    "content": "The City of Ottawa is considering buying a hotel\u00a0to give vulnerable people safe shelter during and after the pandemic, but the plan hinges on other levels of government pitching in.\r\n\"We are realizing that as we look at hotels and we have more positive cases,\u2026 [+3423 chars]"
}