{
    "source": {
        "id": "news24",
        "name": "News24"
    },
    "author": null,
    "title": "News24.com | 'Covid-19 less important because we now fear law enforcement' - family of man killed during lockdown",
    "description": "Three weeks after a Vosloorus man was killed at home, his family is still struggling to come to terms with the events.",
    "url": "https://www.news24.com/SouthAfrica/News/covid-19-less-important-because-we-now-fear-law-enforcement-family-of-man-killed-during-lockdown-20200417",
    "urlToImage": "http://cdn.24.co.za/files/Cms/General/d/10089/e1a1502ae3e649389284f27ac64f8602.jpeg",
    "publishedAt": "2020-04-17T08:36:23Z",
    "content": "\"The minute that incident happened, Covid-19 became almost non-important and less of a fear, because we are now fearing our law enforcement.\"\u00a0\r\nLIVE | All the latest coronavirus and lockdown updates\r\nThese are the sobering words of Ntombikayise Amos, the sist\u2026 [+3841 chars]"
}